flonda/__init__.py
flonda/__main__.py
flonda/cli.py
flonda/flonda.py
flonda/requirements.py
flonda-0.2.dist-info/entry_points.txt
flonda-0.2.dist-info/LICENSE
flonda-0.2.dist-info/WHEEL
flonda-0.2.dist-info/METADATA
flonda-0.2.dist-info/RECORD
