Metadata-Version: 1.2
Name: flonda
Version: 0.2
Summary: Build conda packages using flit
Home-page: https://www.github.com/takluyver/flonda
License: UNKNOWN
Author: Thomas Kluyver
Author-email: thomas@kluyver.me.uk
Classifier: License :: OSI Approved :: MIT License
Requires-Dist: win_cli_launchers
Requires-Dist: flit
